pyintelliclima/__init__.py
pyintelliclima/api.py
pyintelliclima/const.py
pyintelliclima/intelliclima_types.py
pyintelliclima-0.2.1.dist-info/METADATA
pyintelliclima-0.2.1.dist-info/WHEEL
pyintelliclima-0.2.1.dist-info/licenses/LICENSE
pyintelliclima-0.2.1.dist-info/RECORD
