Metadata-Version: 2.4
Name: pyintelliclima
Version: 0.2.1
Summary: Python module for a HTTP API to communicate with the IntelliClima device server.
Project-URL: Repository, https://github.com/dvdinth/pyintelliclima
Author-email: dvdinth <dorus_van_dinther@hotmail.com>
License-Expression: MIT
License-File: LICENSE
Classifier: Development Status :: 4 - Beta
Classifier: Intended Audience :: Developers
Classifier: Operating System :: OS Independent
Classifier: Programming Language :: Python
Classifier: Programming Language :: Python :: 3
Classifier: Programming Language :: Python :: 3.11
Classifier: Programming Language :: Python :: 3.12
Classifier: Programming Language :: Python :: 3.13
Classifier: Typing :: Typed
Requires-Python: <4.0,>=3.11
Requires-Dist: aiohttp>=3.13.2
Requires-Dist: dacite>=1.9.2
